odoo/addons/pos_receipt_usability/README.rst
odoo/addons/pos_receipt_usability/__init__.py
odoo/addons/pos_receipt_usability/__manifest__.py
odoo/addons/pos_receipt_usability/i18n/fr.po
odoo/addons/pos_receipt_usability/i18n/it.po
odoo/addons/pos_receipt_usability/i18n/pos_receipt_usability.pot
odoo/addons/pos_receipt_usability/readme/CONTRIBUTORS.rst
odoo/addons/pos_receipt_usability/readme/DESCRIPTION.rst
odoo/addons/pos_receipt_usability/static/description/icon.png
odoo/addons/pos_receipt_usability/static/description/index.html
odoo/addons/pos_receipt_usability/static/description/with_module.png
odoo/addons/pos_receipt_usability/static/description/without_module.png
odoo/addons/pos_receipt_usability/static/src/css/pos_receipt_usability.scss
odoo/addons/pos_receipt_usability/static/src/xml/PaymentScreen.xml
odoo_addon_pos_receipt_usability-16.0.1.0.0.4.dist-info/METADATA
odoo_addon_pos_receipt_usability-16.0.1.0.0.4.dist-info/WHEEL
odoo_addon_pos_receipt_usability-16.0.1.0.0.4.dist-info/top_level.txt
odoo_addon_pos_receipt_usability-16.0.1.0.0.4.dist-info/RECORD
